{"map":"Arrows","records":[{"time":19.79,"player":"ChrisIsGod@forums"},{"time":20.16,"player":"Rufus@forums"},{"time":20.17,"player":"jimmaaa@forums"},{"time":20.48,"player":"TJohnW@forums"},{"time":20.79,"player":"durf"},{"time":20.84,"player":"tm|cath"},{"time":20.90,"player":"|rash"},{"time":20.92,"player":"nisargisgod@forums"},{"time":21.06,"player":"owned@forums"},{"time":21.09,"player":"alekzander@forums"},{"time":21.58,"player":"DaWg@forums"},{"time":22.89,"player":"rawrica@forums"},{"time":23.42,"player":"what@forums"},{"time":23.57,"player":"WrDq001@forums"},{"time":25.97,"player":"Hub@forums"},{"time":28.87,"player":"Xrobo@forums"},{"time":32.30,"player":"nelg@vertrex.org/Diplomat"}]}